topsis_pallika_102313055/__init__.py
topsis_pallika_102313055/topsis.py
topsis_pallika_102313055-0.1.1.dist-info/METADATA
topsis_pallika_102313055-0.1.1.dist-info/WHEEL
topsis_pallika_102313055-0.1.1.dist-info/entry_points.txt
topsis_pallika_102313055-0.1.1.dist-info/top_level.txt
topsis_pallika_102313055-0.1.1.dist-info/RECORD
