Metadata-Version: 2.4
Name: Topsis-Pallika-102313055
Version: 0.1.1
Summary: A Python package for TOPSIS multi-criteria decision making
Author: Pallika
Author-email: pallika@gmail.com
Requires-Python: >=3.7
Requires-Dist: numpy
Requires-Dist: pandas
Dynamic: author
Dynamic: author-email
Dynamic: description
Dynamic: description-content-type
Dynamic: requires-dist
Dynamic: requires-python
Dynamic: summary
